pywinmem/__init__.py
pywinmem/winmem.py
pywinmem/low/__init__.py
pywinmem/low/pywinmem64.dll
pywinmem/low/pywinmem64_log.dll
pywinmem/low/winmem_decorators.py
pywinmem/low/winmem_low.py
pywinmem/low/winmem_types.py
pywinmem-1.1.0.dist-info/licenses/LICENSE
pywinmem-1.1.0.dist-info/METADATA
pywinmem-1.1.0.dist-info/WHEEL
pywinmem-1.1.0.dist-info/top_level.txt
pywinmem-1.1.0.dist-info/RECORD
