Metadata-Version: 2.4
Name: pywinmem
Version: 1.1.0
Summary: Windows memory manipulation toolkit for Python
Home-page: https://github.com/fuckin_busy/pywinmem
Author: fuckin_busy
Author-email: 
License: GPL-3.0-or-later
Project-URL: Source, https://github.com/fuckin_busy/pywinmem
Keywords: windows,memory,process,ctypes,reverse engineering,game hacking
Classifier: Programming Language :: Python :: 3.10
Classifier: Programming Language :: Python :: 3.11
Classifier: Programming Language :: Python :: 3.12
Classifier: License :: OSI Approved :: GNU General Public License v3 (GPLv3)
Classifier: Operating System :: Microsoft :: Windows
Classifier: Development Status :: 3 - Alpha
Classifier: Intended Audience :: Developers
Classifier: Topic :: Software Development :: Libraries :: Python Modules
Classifier: Topic :: System :: Systems Administration
Requires-Python: >=3.10
License-File: LICENSE
Dynamic: author
Dynamic: classifier
Dynamic: description
Dynamic: description-content-type
Dynamic: home-page
Dynamic: keywords
Dynamic: license
Dynamic: license-file
Dynamic: project-url
Dynamic: requires-python
Dynamic: summary
